{
"skeleton": { "hash": "Rvpy+Bw0yOZ6O4glp4P3bWgMZZ8", "spine": "3.6.53", "width": 1632.13, "height": 3429.16, "images": "" },
"bones": [
	{ "name": "root" },
	{ "name": "line body", "parent": "root", "length": 843.7, "rotation": 89.76, "x": -1.35, "y": 3.48 },
	{ "name": "Guance", "parent": "line body", "x": 151.06, "y": 521.57 },
	{ "name": "Idle face", "parent": "line body", "x": 187.95, "y": 344.22 },
	{ "name": "Smile mouth", "parent": "line body", "x": 149.77, "y": 35.08 },
	{ "name": "ciglia f", "parent": "Idle face", "x": 16.79, "y": 60.44 },
	{ "name": "line body2", "parent": "line body", "length": 184.02, "rotation": 0.11, "x": 843.7 },
	{ "name": "line body4", "parent": "line body2", "length": 161.51, "rotation": 0.75, "x": 183.42, "y": 0.42 },
	{ "name": "line body5", "parent": "line body4", "length": 182.76, "rotation": -0.21, "x": 161.51 },
	{ "name": "line body6", "parent": "line body5", "length": 201.89, "rotation": -1.39, "x": 182.76 },
	{ "name": "line body7", "parent": "line body6", "length": 193.39, "rotation": 1.11, "x": 202.94, "y": -2.11 },
	{ "name": "line body8", "parent": "line body7", "length": 140.27, "rotation": 0.12, "x": 193.39 },
	{ "name": "line body9", "parent": "line body8", "length": 148.75, "rotation": -0.99, "x": 140.27 },
	{ "name": "line leaf", "parent": "line body9", "length": 614.89, "rotation": -0.61, "x": 166.4, "y": 6 },
	{ "name": "line leaf2", "parent": "line leaf", "length": 706.92, "rotation": 0.42, "x": 614.89 }
],
"slots": [
	{ "name": "line leaf", "bone": "line leaf" },
	{ "name": "foglia", "bone": "line leaf", "attachment": "foglia" },
	{ "name": "corpo", "bone": "line body", "attachment": "corpo" },
	{ "name": "line body", "bone": "line body4" },
	{ "name": "Surprised", "bone": "root" },
	{ "name": "Smile mouth", "bone": "Smile mouth", "attachment": "Smile mouth" },
	{ "name": "sadness mouth", "bone": "root" },
	{ "name": "super happiness mouth", "bone": "root" },
	{ "name": "Sleeping face", "bone": "root" },
	{ "name": "ciglia f", "bone": "ciglia f" },
	{ "name": "ciglia", "bone": "ciglia f", "attachment": "ciglia" },
	{ "name": "Idle face", "bone": "Idle face", "attachment": "Idle face" },
	{ "name": "Scared face", "bone": "root" },
	{ "name": "Happiness face", "bone": "root" },
	{ "name": "Sadness face 2", "bone": "root" },
	{ "name": "guancia", "bone": "Guance", "attachment": "guancia" }
],
"skins": {
	"default": {
		"Idle face": {
			"Happiness face": { "x": -2.94, "y": -339.31, "rotation": -89.76, "width": 805, "height": 69 },
			"Idle face": { "x": -2.94, "y": -339.31, "rotation": -89.76, "width": 783, "height": 109 },
			"Sadness face 2": { "x": -2.94, "y": -339.31, "rotation": -89.76, "width": 783, "height": 96 },
			"Scared face": { "x": -2.94, "y": -339.31, "rotation": -89.76, "width": 783, "height": 107 },
			"Sleeping face": { "x": -2.94, "y": -339.31, "rotation": -89.76, "width": 772, "height": 99 }
		},
		"Smile mouth": {
			"Smile mouth": { "x": 8.2, "y": -22.28, "rotation": -89.76, "width": 123, "height": 69 },
			"Surprised": { "x": 8.2, "y": -22.28, "rotation": -89.76, "width": 109, "height": 104 },
			"sadness mouth": { "x": 8.2, "y": -22.28, "rotation": -89.76, "width": 125, "height": 69 },
			"super happiness mouth": { "x": 8.2, "y": -22.28, "rotation": -89.76, "width": 124, "height": 73 }
		}
	},
	"femmina": {
		"ciglia": {
			"ciglia": { "name": "ciglia f", "x": 1.26, "y": -399.79, "rotation": -89.65, "width": 847, "height": 44 }
		},
		"corpo": {
			"corpo": {
				"name": "line body f",
				"type": "mesh",
				"uvs": [ 0.53118, 0.02073, 0.53354, 0.04711, 0.53593, 0.07878, 0.5395, 0.1078, 0.54666, 0.14738, 0.55262, 0.17904, 0.5562, 0.20543, 0.56217, 0.23841, 0.57052, 0.26348, 0.57529, 0.29821, 0.58603, 0.33647, 0.59797, 0.37341, 0.61227, 0.41035, 0.62658, 0.44993, 0.64567, 0.49083, 0.66596, 0.52645, 0.70056, 0.56603, 0.73156, 0.59902, 0.77808, 0.63728, 0.84133, 0.67422, 0.89263, 0.71643, 0.93558, 0.75469, 0.96658, 0.79955, 0.99046, 0.84573, 1, 0.88399, 1, 0.92225, 1, 0.96974, 0.9881, 0.99999, 0.01074, 0.99999, 0, 0.96579, 0, 0.92753, 0, 0.88531, 0.01551, 0.83913, 0.03937, 0.79823, 0.06323, 0.76789, 0.10379, 0.72567, 0.15151, 0.68345, 0.20997, 0.64651, 0.26246, 0.61089, 0.30422, 0.57659, 0.33643, 0.53569, 0.35551, 0.50402, 0.36864, 0.4684, 0.38892, 0.43278, 0.40324, 0.3932, 0.41517, 0.36022, 0.42353, 0.32987, 0.43188, 0.29515, 0.44142, 0.25952, 0.44738, 0.22918, 0.45335, 0.18828, 0.45573, 0.1553, 0.46051, 0.12099, 0.46528, 0.08141, 0.46886, 0.04975, 0.46888, 0.02205, 0.47726, 0, 0.51927, 1.0E-5 ],
				"triangles": [ 2, 54, 1, 2, 53, 54, 54, 0, 1, 54, 55, 0, 55, 57, 0, 55, 56, 57, 4, 52, 3, 3, 53, 2, 3, 52, 53, 49, 6, 7, 6, 50, 5, 6, 49, 50, 5, 51, 4, 5, 50, 51, 4, 51, 52, 10, 46, 9, 46, 47, 9, 47, 8, 9, 8, 48, 7, 8, 47, 48, 48, 49, 7, 12, 44, 11, 12, 43, 44, 11, 45, 10, 11, 44, 45, 10, 45, 46, 14, 42, 13, 13, 43, 12, 13, 42, 43, 16, 40, 15, 15, 41, 14, 15, 40, 41, 14, 41, 42, 28, 29, 27, 27, 29, 26, 26, 30, 25, 26, 29, 30, 30, 31, 25, 31, 24, 25, 24, 32, 23, 24, 31, 32, 32, 33, 23, 33, 22, 23, 33, 34, 22, 34, 21, 22, 34, 20, 21, 34, 35, 20, 35, 19, 20, 35, 36, 19, 36, 18, 19, 36, 37, 18, 18, 38, 17, 18, 37, 38, 17, 39, 16, 17, 38, 39, 16, 39, 40 ],
				"vertices": [ 1, 12, 114.55, -51.62, 1, 2, 11, 199.36, -56.37, 0.02078, 12, 59.92, -55.47, 0.97922, 2, 11, 133.76, -59.22, 0.64357, 12, -5.62, -59.31, 0.35643, 3, 10, 267.23, -63.8, 0.01587, 11, 73.59, -64.1, 0.97979, 12, -65.71, -65.11, 0.00434, 2, 10, 185.17, -74.51, 0.66589, 11, -8.52, -74.48, 0.33411, 2, 10, 119.52, -83.48, 0.98578, 11, -74.2, -83.17, 0.01422, 2, 9, 269.67, -89.37, 0.08635, 10, 64.83, -88.68, 0.91365, 2, 9, 201.5, -99.77, 0.58986, 10, -3.55, -97.61, 0.41014, 3, 8, 329.95, -117.2, 0.0139, 9, 149.74, -113.91, 0.88743, 10, -55.6, -110.62, 0.09867, 2, 8, 257.97, -124.09, 0.16026, 9, 77.94, -122.4, 0.83974, 3, 7, 339.86, -140.91, 0.01839, 8, 178.56, -140.63, 0.58815, 9, -1.09, -140.69, 0.39346, 4, 6, 448.62, -155.41, 4.9E-4, 7, 263.13, -159.31, 0.15628, 8, 101.86, -159.15, 0.76322, 9, -77.36, -160.91, 0.08001, 4, 6, 372.13, -178.72, 0.02601, 7, 186.34, -181.61, 0.45731, 8, 25.11, -181.57, 0.51265, 9, -153.6, -185.02, 0.00403, 4, 1, 1134.72, -200.82, 0.00979, 6, 290.19, -202.02, 0.15892, 7, 104.1, -203.83, 0.64693, 8, -57.11, -203.91, 0.18435, 4, 1, 1050.16, -232.26, 0.07779, 6, 205.5, -233.11, 0.40581, 7, 19.01, -233.8, 0.48382, 8, -142.15, -234.01, 0.03258, 4, 1, 976.54, -265.6, 0.23551, 6, 131.74, -266.15, 0.51116, 7, -55.18, -265.86, 0.25094, 8, -216.29, -266.2, 0.00238, 3, 1, 894.79, -322.34, 0.49829, 6, 49.77, -322.55, 0.41154, 7, -137.89, -321.18, 0.09018, 3, 1, 826.69, -373.19, 0.68975, 6, -18.55, -373.12, 0.27855, 7, -206.86, -370.85, 0.0317, 3, 1, 747.74, -449.39, 0.84541, 6, -97.81, -448.99, 0.14943, 7, -287.11, -445.67, 0.00516, 3, 1, 671.62, -552.83, 0.92688, 6, -174.35, -552.12, 0.07308, 7, -365.01, -547.79, 4.0E-5, 2, 1, 584.51, -636.85, 0.96288, 6, -261.81, -635.78, 0.03712, 2, 1, 505.55, -707.2, 0.98045, 6, -341.06, -705.81, 0.01955, 2, 1, 412.86, -758.13, 0.99052, 6, -433.96, -756.36, 0.00948, 2, 1, 317.41, -797.39, 0.99615, 6, -529.57, -795.22, 0.00385, 2, 1, 238.26, -813.23, 0.99841, 6, -608.78, -810.74, 0.00159, 2, 1, 159.06, -813.5, 0.99956, 6, -687.98, -810.68, 4.4E-4, 2, 1, 60.75, -813.83, 0.99999, 6, -786.3, -810.6, 1.0E-5, 1, 1, -1.93, -794.57, 1, 1, 1, -7.26, 800.43, 1, 1, 1, 63.48, 818.19, 1, 2, 1, 142.68, 818.45, 0.99999, 6, -697.64, 821.33, 1.0E-5, 2, 1, 230.07, 818.75, 0.99959, 6, -610.25, 821.26, 4.1E-4, 2, 1, 325.74, 793.76, 0.99784, 6, -514.69, 795.88, 0.00216, 2, 1, 410.53, 755.1, 0.99396, 6, -430.06, 756.87, 0.00604, 2, 1, 473.48, 716.37, 0.98847, 6, -367.27, 717.89, 0.01153, 2, 1, 561.09, 650.46, 0.97366, 6, -279.93, 651.62, 0.02634, 2, 1, 648.74, 572.88, 0.94545, 6, -192.6, 573.67, 0.05455, 3, 1, 725.53, 477.73, 0.88729, 6, -116.21, 478.21, 0.11234, 7, -293.31, 481.69, 3.7E-4, 3, 1, 799.55, 392.31, 0.77005, 6, -42.54, 392.49, 0.22083, 7, -220.78, 395.01, 0.00912, 3, 1, 870.78, 324.4, 0.5692, 6, 28.42, 324.29, 0.38476, 7, -150.73, 325.88, 0.04604, 4, 1, 955.62, 272.12, 0.28726, 6, 113.04, 271.65, 0.55174, 7, -66.81, 272.14, 0.15957, 8, -228.74, 271.79, 0.00144, 4, 1, 1021.27, 241.18, 0.11513, 6, 178.56, 240.45, 0.54234, 7, -1.7, 240.07, 0.32135, 8, -163.58, 239.82, 0.02119, 4, 1, 1095.08, 220.01, 0.02628, 6, 252.28, 218.98, 0.37053, 7, 71.73, 217.63, 0.50113, 8, -90.12, 217.49, 0.10206, 4, 1, 1168.92, 187.16, 0.00179, 6, 325.99, 185.82, 0.15629, 7, 145, 183.51, 0.50152, 8, -16.8, 183.48, 0.3404, 4, 6, 407.9, 162.39, 0.02966, 7, 226.59, 159.01, 0.23974, 8, 64.84, 159.1, 0.72192, 9, -121.42, 156.45, 0.00868, 4, 6, 476.16, 142.87, 0.00237, 7, 294.59, 138.59, 0.0492, 8, 132.86, 138.79, 0.82519, 9, -52.96, 137.65, 0.12324, 3, 7, 357.21, 124.08, 0.00216, 8, 195.51, 124.38, 0.51795, 9, 9.98, 124.63, 0.47989, 3, 8, 267.22, 109.86, 0.1043, 9, 82, 111.71, 0.89529, 10, -118.48, 116.4, 4.1E-4, 3, 8, 340.75, 93.37, 6.7E-4, 9, 155.88, 96.85, 0.87951, 10, -44.93, 99.95, 0.11982, 2, 9, 218.79, 87.73, 0.40301, 10, 17.77, 89.48, 0.59699, 3, 9, 303.54, 78.82, 0.00937, 10, 102.31, 78.75, 0.98678, 11, -90.74, 79.13, 0.00385, 2, 10, 170.53, 74.06, 0.77337, 11, -22.54, 74.15, 0.22663, 2, 10, 241.44, 65.43, 0.09668, 11, 48.34, 65.23, 0.90332, 2, 11, 130.13, 56.14, 0.69308, 12, -11, 55.98, 0.30692, 2, 11, 195.58, 49.26, 0.02698, 12, 54.54, 50.09, 0.97302, 1, 12, 111.89, 50.04, 1, 1, 12, 157.52, 36.38, 1, 1, 12, 157.44, -32.18, 1 ],
				"hull": 58,
				"edges": [ 54, 56, 112, 114, 110, 112, 0, 114, 110, 0, 108, 110, 0, 2, 108, 2, 106, 108, 2, 4, 106, 4, 104, 106, 4, 6, 104, 6, 102, 104, 6, 8, 102, 8, 100, 102, 8, 10, 100, 10, 98, 100, 10, 12, 98, 12, 96, 98, 12, 14, 96, 14, 94, 96, 14, 16, 94, 16, 92, 94, 16, 18, 92, 18, 90, 92, 18, 20, 90, 20, 88, 90, 20, 22, 88, 22, 86, 88, 22, 24, 86, 24, 84, 86, 24, 26, 84, 26, 82, 84, 26, 28, 82, 28, 80, 82, 28, 30, 80, 30, 78, 80, 30, 32, 78, 32, 76, 78, 32, 34, 76, 34, 74, 76, 34, 36, 74, 36, 72, 74, 36, 38, 72, 38, 70, 72, 38, 40, 70, 40, 68, 70, 40, 42, 68, 42, 66, 68, 42, 44, 66, 44, 64, 66, 44, 46, 64, 46, 62, 64, 46, 48, 62, 48, 60, 62, 48, 50, 60, 50, 56, 58, 58, 60, 50, 52, 52, 54, 58, 52 ],
				"width": 1632,
				"height": 2070
			}
		},
		"foglia": {
			"foglia": { "name": "line leaf f", "x": 628.24, "y": -0.35, "rotation": -89.15, "width": 829, "height": 1436 }
		},
		"guancia": {
			"guancia": { "name": "Guance f", "x": 0.49, "y": -518.8, "rotation": -89.76, "width": 1153, "height": 66 }
		}
	},
	"maschio": {
		"corpo": {
			"corpo": {
				"name": "line body",
				"type": "mesh",
				"uvs": [ 0.53118, 0.02073, 0.53354, 0.04711, 0.53593, 0.07878, 0.5395, 0.1078, 0.54666, 0.14738, 0.55262, 0.17904, 0.5562, 0.20543, 0.56217, 0.23841, 0.57052, 0.26348, 0.57529, 0.29821, 0.58603, 0.33647, 0.59797, 0.37341, 0.61227, 0.41035, 0.62658, 0.44993, 0.64567, 0.49083, 0.66596, 0.52645, 0.70056, 0.56603, 0.73156, 0.59902, 0.77808, 0.63728, 0.84133, 0.67422, 0.89263, 0.71643, 0.93558, 0.75469, 0.96658, 0.79955, 0.99046, 0.84573, 1, 0.88399, 1, 0.92225, 1, 0.96974, 0.9881, 0.99999, 0.01074, 0.99999, 0, 0.96579, 0, 0.92753, 0, 0.88531, 0.01551, 0.83913, 0.03937, 0.79823, 0.06323, 0.76789, 0.10379, 0.72567, 0.15151, 0.68345, 0.20997, 0.64651, 0.26246, 0.61089, 0.30422, 0.57659, 0.33643, 0.53569, 0.35551, 0.50402, 0.36864, 0.4684, 0.38892, 0.43278, 0.40324, 0.3932, 0.41517, 0.36022, 0.42353, 0.32987, 0.43188, 0.29515, 0.44142, 0.25952, 0.44738, 0.22918, 0.45335, 0.18828, 0.45573, 0.1553, 0.46051, 0.12099, 0.46528, 0.08141, 0.46886, 0.04975, 0.46888, 0.02205, 0.47726, 0, 0.51927, 1.0E-5 ],
				"triangles": [ 2, 54, 1, 2, 53, 54, 54, 0, 1, 54, 55, 0, 55, 57, 0, 55, 56, 57, 4, 52, 3, 3, 53, 2, 3, 52, 53, 49, 6, 7, 6, 50, 5, 6, 49, 50, 5, 51, 4, 5, 50, 51, 4, 51, 52, 10, 46, 9, 46, 47, 9, 47, 8, 9, 8, 48, 7, 8, 47, 48, 48, 49, 7, 12, 44, 11, 12, 43, 44, 11, 45, 10, 11, 44, 45, 10, 45, 46, 14, 42, 13, 13, 43, 12, 13, 42, 43, 16, 40, 15, 15, 41, 14, 15, 40, 41, 14, 41, 42, 28, 29, 27, 27, 29, 26, 26, 30, 25, 26, 29, 30, 30, 31, 25, 31, 24, 25, 24, 32, 23, 24, 31, 32, 32, 33, 23, 33, 22, 23, 33, 34, 22, 34, 21, 22, 34, 20, 21, 34, 35, 20, 35, 19, 20, 35, 36, 19, 36, 18, 19, 36, 37, 18, 18, 38, 17, 18, 37, 38, 17, 39, 16, 17, 38, 39, 16, 39, 40 ],
				"vertices": [ 1, 12, 111.73, -49.37, 1, 2, 11, 196.56, -54.13, 0.02078, 12, 57.11, -53.27, 0.97922, 2, 11, 130.96, -57.03, 0.64357, 12, -8.44, -57.16, 0.35643, 3, 10, 264.44, -61.66, 0.01587, 11, 70.8, -61.96, 0.97979, 12, -68.52, -63, 0.00434, 2, 10, 182.39, -72.44, 0.66589, 11, -11.3, -72.4, 0.33411, 2, 10, 116.74, -81.46, 0.98578, 11, -76.98, -81.14, 0.01422, 2, 9, 266.85, -87.46, 0.08635, 10, 62.06, -86.7, 0.91365, 2, 9, 198.68, -97.91, 0.58986, 10, -6.31, -95.68, 0.41014, 3, 8, 327.19, -115.31, 0.0139, 9, 146.94, -112.08, 0.88743, 10, -58.35, -108.74, 0.09867, 2, 8, 255.21, -122.26, 0.16026, 9, 75.14, -120.63, 0.83974, 3, 7, 337.12, -139.13, 0.01839, 8, 175.82, -138.86, 0.58815, 9, -3.87, -138.98, 0.39346, 4, 6, 445.87, -153.74, 4.9E-4, 7, 260.4, -157.59, 0.15628, 8, 99.13, -157.44, 0.76322, 9, -80.13, -159.26, 0.08001, 4, 6, 369.4, -177.1, 0.02601, 7, 183.63, -179.95, 0.45731, 8, 22.39, -179.92, 0.51265, 9, -156.34, -183.42, 0.00403, 4, 1, 1132, -199.28, 0.00979, 6, 287.47, -200.46, 0.15892, 7, 101.4, -202.23, 0.64693, 8, -59.8, -202.33, 0.18435, 4, 1, 1047.46, -230.78, 0.07779, 6, 202.81, -231.62, 0.40581, 7, 16.34, -232.27, 0.48382, 8, -144.82, -232.49, 0.03258, 4, 1, 973.86, -264.18, 0.23551, 6, 129.07, -264.71, 0.51116, 7, -57.83, -264.4, 0.25094, 8, -218.94, -264.73, 0.00238, 3, 1, 892.17, -320.98, 0.49829, 6, 47.14, -321.18, 0.41154, 7, -140.49, -319.78, 0.09018, 3, 1, 824.1, -371.88, 0.68975, 6, -21.13, -371.8, 0.27855, 7, -209.43, -369.5, 0.0317, 3, 1, 745.22, -448.14, 0.84541, 6, -100.33, -447.73, 0.14943, 7, -289.62, -444.38, 0.00516, 3, 1, 669.17, -551.65, 0.92688, 6, -176.8, -550.92, 0.07308, 7, -367.44, -546.56, 4.0E-5, 2, 1, 582.13, -635.73, 0.96288, 6, -264.19, -634.64, 0.03712, 2, 1, 503.22, -706.14, 0.98045, 6, -343.39, -704.74, 0.01955, 2, 1, 410.57, -757.15, 0.99052, 6, -436.24, -755.36, 0.00948, 2, 1, 315.15, -796.48, 0.99615, 6, -531.83, -794.3, 0.00385, 2, 1, 236.01, -812.38, 0.99841, 6, -611.03, -809.87, 0.00159, 2, 1, 156.81, -812.71, 0.99956, 6, -690.23, -809.87, 4.4E-4, 2, 1, 58.5, -813.11, 0.99999, 6, -788.54, -809.87, 1.0E-5, 1, 1, -4.19, -793.9, 1, 1, 1, -10.75, 801.09, 1, 1, 1, 59.98, 818.91, 1, 2, 1, 139.18, 819.23, 0.99999, 6, -701.15, 822.13, 1.0E-5, 2, 1, 226.57, 819.59, 0.99959, 6, -613.76, 822.13, 4.1E-4, 2, 1, 322.25, 794.68, 0.99784, 6, -518.17, 796.82, 0.00216, 2, 1, 407.08, 756.08, 0.99396, 6, -433.51, 757.88, 0.00604, 2, 1, 470.05, 717.4, 0.98847, 6, -370.7, 718.94, 0.01153, 2, 1, 557.71, 651.57, 0.97366, 6, -283.31, 652.74, 0.02634, 2, 1, 645.42, 574.05, 0.94545, 6, -195.92, 574.86, 0.05455, 3, 1, 722.28, 478.96, 0.88729, 6, -119.45, 479.45, 0.11234, 7, -296.54, 482.98, 3.7E-4, 3, 1, 796.37, 393.59, 0.77005, 6, -45.71, 393.79, 0.22083, 7, -223.93, 396.35, 0.00912, 3, 1, 867.66, 325.74, 0.5692, 6, 25.29, 325.64, 0.38476, 7, -153.83, 327.27, 0.04604, 4, 1, 952.53, 273.52, 0.28726, 6, 109.96, 273.07, 0.55174, 7, -69.87, 273.6, 0.15957, 8, -231.8, 273.24, 0.00144, 4, 1, 1018.21, 242.64, 0.11513, 6, 175.5, 241.92, 0.54234, 7, -4.74, 241.58, 0.32135, 8, -166.62, 241.33, 0.02119, 4, 1, 1092.03, 221.53, 0.02628, 6, 249.24, 220.5, 0.37053, 7, 68.71, 219.2, 0.50113, 8, -93.14, 219.06, 0.10206, 4, 1, 1165.9, 188.73, 0.00179, 6, 322.97, 187.4, 0.15629, 7, 142, 185.13, 0.50152, 8, -19.79, 185.1, 0.3404, 4, 6, 404.9, 164.04, 0.02966, 7, 223.62, 160.69, 0.23974, 8, 61.86, 160.79, 0.72192, 9, -124.43, 158.07, 0.00868, 4, 6, 473.18, 144.57, 0.00237, 7, 291.63, 140.33, 0.0492, 8, 129.9, 140.52, 0.82519, 9, -55.96, 139.32, 0.12324, 3, 7, 354.26, 125.87, 0.00216, 8, 192.55, 126.17, 0.51795, 9, 6.99, 126.35, 0.47989, 3, 8, 264.28, 111.7, 0.1043, 9, 79.02, 113.48, 0.89529, 10, -121.4, 118.23, 4.1E-4, 3, 8, 337.83, 95.27, 6.7E-4, 9, 152.92, 98.68, 0.87951, 10, -47.84, 101.85, 0.11982, 2, 9, 215.83, 89.61, 0.40301, 10, 14.86, 91.42, 0.59699, 3, 9, 300.59, 80.77, 0.00937, 10, 99.41, 80.76, 0.98678, 11, -93.64, 81.15, 0.00385, 2, 10, 167.64, 76.12, 0.77337, 11, -25.43, 76.22, 0.22663, 2, 10, 238.55, 67.55, 0.09668, 11, 45.45, 67.36, 0.90332, 2, 11, 127.25, 58.33, 0.69308, 12, -13.9, 58.13, 0.30692, 2, 11, 192.7, 51.5, 0.02698, 12, 51.65, 52.29, 0.97302, 1, 12, 109, 52.29, 1, 1, 12, 154.63, 38.66, 1, 1, 12, 154.61, -29.9, 1 ],
				"hull": 58,
				"edges": [ 54, 56, 112, 114, 110, 112, 0, 114, 110, 0, 108, 110, 0, 2, 108, 2, 106, 108, 2, 4, 106, 4, 104, 106, 4, 6, 104, 6, 102, 104, 6, 8, 102, 8, 100, 102, 8, 10, 100, 10, 98, 100, 10, 12, 98, 12, 96, 98, 12, 14, 96, 14, 94, 96, 14, 16, 94, 16, 92, 94, 16, 18, 92, 18, 90, 92, 18, 20, 90, 20, 88, 90, 20, 22, 88, 22, 86, 88, 22, 24, 86, 24, 84, 86, 24, 26, 84, 26, 82, 84, 26, 28, 82, 28, 80, 82, 28, 30, 80, 30, 78, 80, 30, 32, 78, 32, 76, 78, 32, 34, 76, 34, 74, 76, 34, 36, 74, 36, 72, 74, 36, 38, 72, 38, 70, 72, 38, 40, 70, 40, 68, 70, 40, 42, 68, 42, 66, 68, 42, 44, 66, 44, 64, 66, 44, 46, 64, 46, 62, 64, 46, 48, 62, 48, 60, 62, 48, 50, 60, 50, 56, 58, 58, 60, 50, 52, 52, 54, 58, 52 ],
				"width": 1632,
				"height": 2070
			}
		},
		"foglia": {
			"foglia": { "name": "line leaf", "x": 628.27, "y": -0.32, "rotation": -89.39, "width": 829, "height": 1436 }
		},
		"guancia": {
			"guancia": { "name": "Guance", "x": 0.45, "y": -518.79, "rotation": -89.76, "width": 1153, "height": 66 }
		}
	}
},
"animations": {
	"dormita": {
		"slots": {
			"Idle face": {
				"attachment": [
					{ "time": 0, "name": "Sleeping face" }
				]
			},
			"Smile mouth": {
				"attachment": [
					{ "time": 0, "name": "Smile mouth" }
				]
			},
			"ciglia": {
				"attachment": [
					{ "time": 0, "name": null }
				]
			}
		},
		"bones": {
			"line body5": {
				"rotate": [
					{ "time": 0, "angle": 3.28 },
					{ "time": 0.8, "angle": -3.09 },
					{ "time": 2, "angle": 3.28 }
				],
				"translate": [
					{ "time": 0, "x": 0, "y": 0, "curve": "stepped" },
					{ "time": 2, "x": 0, "y": 0 }
				],
				"scale": [
					{ "time": 0, "x": 1, "y": 1, "curve": "stepped" },
					{ "time": 2, "x": 1, "y": 1 }
				],
				"shear": [
					{ "time": 0, "x": 0, "y": 0, "curve": "stepped" },
					{ "time": 2, "x": 0, "y": 0 }
				]
			},
			"Idle face": {
				"rotate": [
					{ "time": 0, "angle": 0 }
				],
				"translate": [
					{ "time": 0, "x": 0, "y": 0 }
				],
				"scale": [
					{ "time": 0, "x": 1, "y": 1 }
				],
				"shear": [
					{ "time": 0, "x": 0, "y": 0 }
				]
			},
			"line body7": {
				"rotate": [
					{ "time": 0, "angle": 27.52 },
					{ "time": 0.8, "angle": 29.36 },
					{ "time": 2, "angle": 27.52 }
				],
				"translate": [
					{ "time": 0, "x": 0, "y": 0, "curve": "stepped" },
					{ "time": 2, "x": 0, "y": 0 }
				],
				"scale": [
					{ "time": 0, "x": 1, "y": 1, "curve": "stepped" },
					{ "time": 2, "x": 1, "y": 1 }
				],
				"shear": [
					{ "time": 0, "x": 0, "y": 0, "curve": "stepped" },
					{ "time": 2, "x": 0, "y": 0 }
				]
			},
			"line leaf": {
				"rotate": [
					{ "time": 0, "angle": 0 }
				],
				"translate": [
					{ "time": 0, "x": 0, "y": 0 }
				],
				"scale": [
					{ "time": 0, "x": 1, "y": 1 }
				],
				"shear": [
					{ "time": 0, "x": 0, "y": 0 }
				]
			},
			"line body2": {
				"rotate": [
					{ "time": 0, "angle": 3.28 },
					{ "time": 0.8, "angle": -3.09 },
					{ "time": 2, "angle": 3.28 }
				],
				"translate": [
					{ "time": 0, "x": 0, "y": 0, "curve": "stepped" },
					{ "time": 2, "x": 0, "y": 0 }
				],
				"scale": [
					{ "time": 0, "x": 1, "y": 1, "curve": "stepped" },
					{ "time": 2, "x": 1, "y": 1 }
				],
				"shear": [
					{ "time": 0, "x": 0, "y": 0, "curve": "stepped" },
					{ "time": 2, "x": 0, "y": 0 }
				]
			},
			"line body8": {
				"rotate": [
					{ "time": 0, "angle": 27.52 },
					{ "time": 0.8, "angle": 29.36 },
					{ "time": 2, "angle": 27.52 }
				],
				"translate": [
					{ "time": 0, "x": 0, "y": 0, "curve": "stepped" },
					{ "time": 2, "x": 0, "y": 0 }
				],
				"scale": [
					{ "time": 0, "x": 1, "y": 1, "curve": "stepped" },
					{ "time": 2, "x": 1, "y": 1 }
				],
				"shear": [
					{ "time": 0, "x": 0, "y": 0, "curve": "stepped" },
					{ "time": 2, "x": 0, "y": 0 }
				]
			},
			"line body9": {
				"rotate": [
					{ "time": 0, "angle": 27.52 },
					{ "time": 0.8, "angle": 29.36 },
					{ "time": 2, "angle": 27.52 }
				],
				"translate": [
					{ "time": 0, "x": 0, "y": 0, "curve": "stepped" },
					{ "time": 2, "x": 0, "y": 0 }
				],
				"scale": [
					{ "time": 0, "x": 1, "y": 1, "curve": "stepped" },
					{ "time": 2, "x": 1, "y": 1 }
				],
				"shear": [
					{ "time": 0, "x": 0, "y": 0, "curve": "stepped" },
					{ "time": 2, "x": 0, "y": 0 }
				]
			},
			"Smile mouth": {
				"rotate": [
					{ "time": 0, "angle": 0 }
				],
				"translate": [
					{ "time": 0, "x": 0, "y": 0 }
				],
				"scale": [
					{ "time": 0, "x": 1, "y": 1 }
				],
				"shear": [
					{ "time": 0, "x": 0, "y": 0 }
				]
			},
			"line body4": {
				"rotate": [
					{ "time": 0, "angle": 27.52 },
					{ "time": 0.8, "angle": 29.36 },
					{ "time": 2, "angle": 27.52 }
				],
				"translate": [
					{ "time": 0, "x": 0, "y": 0, "curve": "stepped" },
					{ "time": 2, "x": 0, "y": 0 }
				],
				"scale": [
					{ "time": 0, "x": 1, "y": 1, "curve": "stepped" },
					{ "time": 2, "x": 1, "y": 1 }
				],
				"shear": [
					{ "time": 0, "x": 0, "y": 0, "curve": "stepped" },
					{ "time": 2, "x": 0, "y": 0 }
				]
			},
			"line leaf2": {
				"rotate": [
					{ "time": 0, "angle": 0 }
				],
				"translate": [
					{ "time": 0, "x": 0, "y": 0 }
				],
				"scale": [
					{ "time": 0, "x": 1, "y": 1 }
				],
				"shear": [
					{ "time": 0, "x": 0, "y": 0 }
				]
			},
			"Guance": {
				"rotate": [
					{ "time": 0, "angle": 0 }
				],
				"translate": [
					{ "time": 0, "x": 0, "y": 0 }
				],
				"scale": [
					{ "time": 0, "x": 1, "y": 1 }
				],
				"shear": [
					{ "time": 0, "x": 0, "y": 0 }
				]
			},
			"line body6": {
				"rotate": [
					{ "time": 0, "angle": 27.52 },
					{ "time": 0.8, "angle": 29.36 },
					{ "time": 2, "angle": 27.52 }
				],
				"translate": [
					{ "time": 0, "x": 0, "y": 0, "curve": "stepped" },
					{ "time": 2, "x": 0, "y": 0 }
				],
				"scale": [
					{ "time": 0, "x": 1, "y": 1, "curve": "stepped" },
					{ "time": 2, "x": 1, "y": 1 }
				],
				"shear": [
					{ "time": 0, "x": 0, "y": 0, "curve": "stepped" },
					{ "time": 2, "x": 0, "y": 0 }
				]
			},
			"line body": {
				"rotate": [
					{ "time": 0, "angle": 0, "curve": "stepped" },
					{ "time": 1.3333, "angle": 0 }
				],
				"translate": [
					{ "time": 0, "x": 0, "y": 0, "curve": "stepped" },
					{ "time": 1.3333, "x": 0, "y": 0 }
				],
				"scale": [
					{ "time": 0, "x": 1, "y": 1 },
					{ "time": 0.6667, "x": 1, "y": 0.918 },
					{ "time": 1.3333, "x": 1, "y": 1 }
				],
				"shear": [
					{ "time": 0, "x": 0, "y": 0, "curve": "stepped" },
					{ "time": 1.3333, "x": 0, "y": 0 }
				]
			},
			"root": {
				"rotate": [
					{ "time": 0, "angle": 0 }
				],
				"translate": [
					{ "time": 0, "x": 0, "y": 0 }
				],
				"scale": [
					{ "time": 0, "x": 1, "y": 1 }
				],
				"shear": [
					{ "time": 0, "x": 0, "y": 0 }
				]
			},
			"ciglia f": {
				"rotate": [
					{ "time": 0, "angle": 0, "curve": "stepped" },
					{ "time": 2, "angle": 0 }
				],
				"translate": [
					{ "time": 0, "x": -20.49, "y": -1.79, "curve": "stepped" },
					{ "time": 2, "x": -20.49, "y": -1.79 }
				]
			}
		}
	},
	"felice": {
		"slots": {
			"Idle face": {
				"attachment": [
					{ "time": 0, "name": "Happiness face" },
					{ "time": 0.3333, "name": "Happiness face" }
				]
			},
			"Smile mouth": {
				"attachment": [
					{ "time": 0, "name": "super happiness mouth" },
					{ "time": 0.3333, "name": "super happiness mouth" }
				]
			},
			"ciglia": {
				"attachment": [
					{ "time": 0, "name": null }
				]
			}
		},
		"bones": {
			"root": {
				"rotate": [
					{ "time": 0, "angle": 0, "curve": "stepped" },
					{ "time": 0.6667, "angle": 0 }
				],
				"translate": [
					{ "time": 0, "x": 0, "y": 0, "curve": "stepped" },
					{ "time": 0.6667, "x": 0, "y": 0 }
				],
				"scale": [
					{ "time": 0, "x": 1, "y": 1, "curve": "stepped" },
					{ "time": 0.6667, "x": 1, "y": 1 }
				],
				"shear": [
					{ "time": 0, "x": 0, "y": 0, "curve": "stepped" },
					{ "time": 0.6667, "x": 0, "y": 0 }
				]
			},
			"line body": {
				"rotate": [
					{ "time": 0, "angle": 0, "curve": "stepped" },
					{ "time": 1.6667, "angle": 0 }
				],
				"translate": [
					{ "time": 0, "x": 0, "y": 0, "curve": "stepped" },
					{ "time": 1.6667, "x": 0, "y": 0 }
				],
				"scale": [
					{ "time": 0, "x": 1, "y": 1 },
					{ "time": 0.7333, "x": 1, "y": 1.086 },
					{ "time": 1.6667, "x": 1, "y": 1 }
				],
				"shear": [
					{ "time": 0, "x": 0, "y": 0, "curve": "stepped" },
					{ "time": 1.6667, "x": 0, "y": 0 }
				]
			},
			"line body2": {
				"rotate": [
					{ "time": 0, "angle": 3.69 },
					{ "time": 0.1667, "angle": -3.61 },
					{ "time": 0.3333, "angle": 3.69 },
					{ "time": 0.5, "angle": -3.61 },
					{ "time": 0.6667, "angle": 3.69 },
					{ "time": 0.8333, "angle": -3.61 },
					{ "time": 1, "angle": 3.69 },
					{ "time": 1.1667, "angle": -3.61 },
					{ "time": 1.3333, "angle": 3.69 },
					{ "time": 1.5, "angle": -3.61 },
					{ "time": 1.6667, "angle": 3.69 }
				],
				"translate": [
					{ "time": 0, "x": 0, "y": 0, "curve": "stepped" },
					{ "time": 0.3333, "x": 0, "y": 0 },
					{ "time": 0.4333, "x": -0.04, "y": 8.56 },
					{ "time": 0.6667, "x": 0, "y": 0, "curve": "stepped" },
					{ "time": 1, "x": 0, "y": 0, "curve": "stepped" },
					{ "time": 1.3333, "x": 0, "y": 0, "curve": "stepped" },
					{ "time": 1.6667, "x": 0, "y": 0 }
				],
				"scale": [
					{ "time": 0, "x": 1, "y": 1, "curve": "stepped" },
					{ "time": 0.3333, "x": 1, "y": 1, "curve": "stepped" },
					{ "time": 0.6667, "x": 1, "y": 1, "curve": "stepped" },
					{ "time": 1, "x": 1, "y": 1, "curve": "stepped" },
					{ "time": 1.3333, "x": 1, "y": 1, "curve": "stepped" },
					{ "time": 1.6667, "x": 1, "y": 1 }
				],
				"shear": [
					{ "time": 0, "x": 0, "y": 0, "curve": "stepped" },
					{ "time": 0.3333, "x": 0, "y": 0, "curve": "stepped" },
					{ "time": 0.6667, "x": 0, "y": 0, "curve": "stepped" },
					{ "time": 1, "x": 0, "y": 0, "curve": "stepped" },
					{ "time": 1.3333, "x": 0, "y": 0, "curve": "stepped" },
					{ "time": 1.6667, "x": 0, "y": 0 }
				]
			},
			"line body4": {
				"rotate": [
					{ "time": 0, "angle": 3.69 },
					{ "time": 0.1667, "angle": -3.61 },
					{ "time": 0.3333, "angle": 3.69 },
					{ "time": 0.5, "angle": -3.61 },
					{ "time": 0.6667, "angle": 3.69 },
					{ "time": 0.8333, "angle": -3.61 },
					{ "time": 1, "angle": 3.69 },
					{ "time": 1.1667, "angle": -3.61 },
					{ "time": 1.3333, "angle": 3.69 },
					{ "time": 1.5, "angle": -3.61 },
					{ "time": 1.6667, "angle": 3.69 }
				],
				"translate": [
					{ "time": 0, "x": 0, "y": 0, "curve": "stepped" },
					{ "time": 0.3333, "x": 0, "y": 0, "curve": "stepped" },
					{ "time": 0.6667, "x": 0, "y": 0, "curve": "stepped" },
					{ "time": 1, "x": 0, "y": 0, "curve": "stepped" },
					{ "time": 1.3333, "x": 0, "y": 0, "curve": "stepped" },
					{ "time": 1.6667, "x": 0, "y": 0 }
				],
				"scale": [
					{ "time": 0, "x": 1, "y": 1, "curve": "stepped" },
					{ "time": 0.3333, "x": 1, "y": 1, "curve": "stepped" },
					{ "time": 0.6667, "x": 1, "y": 1, "curve": "stepped" },
					{ "time": 1, "x": 1, "y": 1, "curve": "stepped" },
					{ "time": 1.3333, "x": 1, "y": 1, "curve": "stepped" },
					{ "time": 1.6667, "x": 1, "y": 1 }
				],
				"shear": [
					{ "time": 0, "x": 0, "y": 0, "curve": "stepped" },
					{ "time": 0.3333, "x": 0, "y": 0, "curve": "stepped" },
					{ "time": 0.6667, "x": 0, "y": 0, "curve": "stepped" },
					{ "time": 1, "x": 0, "y": 0, "curve": "stepped" },
					{ "time": 1.3333, "x": 0, "y": 0, "curve": "stepped" },
					{ "time": 1.6667, "x": 0, "y": 0 }
				]
			},
			"line body5": {
				"rotate": [
					{ "time": 0, "angle": 3.69 },
					{ "time": 0.1667, "angle": -3.61 },
					{ "time": 0.3333, "angle": 3.69 },
					{ "time": 0.5, "angle": -3.61 },
					{ "time": 0.6667, "angle": 3.69 },
					{ "time": 0.8333, "angle": -3.61 },
					{ "time": 1, "angle": 3.69 },
					{ "time": 1.1667, "angle": -3.61 },
					{ "time": 1.3333, "angle": 3.69 },
					{ "time": 1.5, "angle": -3.61 },
					{ "time": 1.6667, "angle": 3.69 }
				],
				"translate": [
					{ "time": 0, "x": 0, "y": 0, "curve": "stepped" },
					{ "time": 0.3333, "x": 0, "y": 0, "curve": "stepped" },
					{ "time": 0.6667, "x": 0, "y": 0, "curve": "stepped" },
					{ "time": 1, "x": 0, "y": 0, "curve": "stepped" },
					{ "time": 1.3333, "x": 0, "y": 0, "curve": "stepped" },
					{ "time": 1.6667, "x": 0, "y": 0 }
				],
				"scale": [
					{ "time": 0, "x": 1, "y": 1, "curve": "stepped" },
					{ "time": 0.3333, "x": 1, "y": 1, "curve": "stepped" },
					{ "time": 0.6667, "x": 1, "y": 1, "curve": "stepped" },
					{ "time": 1, "x": 1, "y": 1, "curve": "stepped" },
					{ "time": 1.3333, "x": 1, "y": 1, "curve": "stepped" },
					{ "time": 1.6667, "x": 1, "y": 1 }
				],
				"shear": [
					{ "time": 0, "x": 0, "y": 0, "curve": "stepped" },
					{ "time": 0.3333, "x": 0, "y": 0, "curve": "stepped" },
					{ "time": 0.6667, "x": 0, "y": 0, "curve": "stepped" },
					{ "time": 1, "x": 0, "y": 0, "curve": "stepped" },
					{ "time": 1.3333, "x": 0, "y": 0, "curve": "stepped" },
					{ "time": 1.6667, "x": 0, "y": 0 }
				]
			},
			"line body6": {
				"rotate": [
					{ "time": 0, "angle": 3.69 },
					{ "time": 0.1667, "angle": -3.61 },
					{ "time": 0.3333, "angle": 3.69 },
					{ "time": 0.5, "angle": -3.61 },
					{ "time": 0.6667, "angle": 3.69 },
					{ "time": 0.8333, "angle": -3.61 },
					{ "time": 1, "angle": 3.69 },
					{ "time": 1.1667, "angle": -3.61 },
					{ "time": 1.3333, "angle": 3.69 },
					{ "time": 1.5, "angle": -3.61 },
					{ "time": 1.6667, "angle": 3.69 }
				],
				"translate": [
					{ "time": 0, "x": 0, "y": 0, "curve": "stepped" },
					{ "time": 0.3333, "x": 0, "y": 0, "curve": "stepped" },
					{ "time": 0.6667, "x": 0, "y": 0, "curve": "stepped" },
					{ "time": 1, "x": 0, "y": 0, "curve": "stepped" },
					{ "time": 1.3333, "x": 0, "y": 0, "curve": "stepped" },
					{ "time": 1.6667, "x": 0, "y": 0 }
				],
				"scale": [
					{ "time": 0, "x": 1, "y": 1, "curve": "stepped" },
					{ "time": 0.3333, "x": 1, "y": 1, "curve": "stepped" },
					{ "time": 0.6667, "x": 1, "y": 1, "curve": "stepped" },
					{ "time": 1, "x": 1, "y": 1, "curve": "stepped" },
					{ "time": 1.3333, "x": 1, "y": 1, "curve": "stepped" },
					{ "time": 1.6667, "x": 1, "y": 1 }
				],
				"shear": [
					{ "time": 0, "x": 0, "y": 0, "curve": "stepped" },
					{ "time": 0.3333, "x": 0, "y": 0, "curve": "stepped" },
					{ "time": 0.6667, "x": 0, "y": 0, "curve": "stepped" },
					{ "time": 1, "x": 0, "y": 0, "curve": "stepped" },
					{ "time": 1.3333, "x": 0, "y": 0, "curve": "stepped" },
					{ "time": 1.6667, "x": 0, "y": 0 }
				]
			},
			"line body7": {
				"rotate": [
					{ "time": 0, "angle": 3.69 },
					{ "time": 0.1667, "angle": -3.61 },
					{ "time": 0.3333, "angle": 3.69 },
					{ "time": 0.5, "angle": -3.61 },
					{ "time": 0.6667, "angle": 3.69 },
					{ "time": 0.8333, "angle": -3.61 },
					{ "time": 1, "angle": 3.69 },
					{ "time": 1.1667, "angle": -3.61 },
					{ "time": 1.3333, "angle": 3.69 },
					{ "time": 1.5, "angle": -3.61 },
					{ "time": 1.6667, "angle": 3.69 }
				],
				"translate": [
					{ "time": 0, "x": 0, "y": 0, "curve": "stepped" },
					{ "time": 0.3333, "x": 0, "y": 0, "curve": "stepped" },
					{ "time": 0.6667, "x": 0, "y": 0, "curve": "stepped" },
					{ "time": 1, "x": 0, "y": 0, "curve": "stepped" },
					{ "time": 1.3333, "x": 0, "y": 0, "curve": "stepped" },
					{ "time": 1.6667, "x": 0, "y": 0 }
				],
				"scale": [
					{ "time": 0, "x": 1, "y": 1, "curve": "stepped" },
					{ "time": 0.3333, "x": 1, "y": 1, "curve": "stepped" },
					{ "time": 0.6667, "x": 1, "y": 1, "curve": "stepped" },
					{ "time": 1, "x": 1, "y": 1, "curve": "stepped" },
					{ "time": 1.3333, "x": 1, "y": 1, "curve": "stepped" },
					{ "time": 1.6667, "x": 1, "y": 1 }
				],
				"shear": [
					{ "time": 0, "x": 0, "y": 0, "curve": "stepped" },
					{ "time": 0.3333, "x": 0, "y": 0, "curve": "stepped" },
					{ "time": 0.6667, "x": 0, "y": 0, "curve": "stepped" },
					{ "time": 1, "x": 0, "y": 0, "curve": "stepped" },
					{ "time": 1.3333, "x": 0, "y": 0, "curve": "stepped" },
					{ "time": 1.6667, "x": 0, "y": 0 }
				]
			},
			"line body8": {
				"rotate": [
					{ "time": 0, "angle": 3.69 },
					{ "time": 0.1667, "angle": -3.61 },
					{ "time": 0.3333, "angle": 3.69 },
					{ "time": 0.5, "angle": -3.61 },
					{ "time": 0.6667, "angle": 3.69 },
					{ "time": 0.8333, "angle": -3.61 },
					{ "time": 1, "angle": 3.69 },
					{ "time": 1.1667, "angle": -3.61 },
					{ "time": 1.3333, "angle": 3.69 },
					{ "time": 1.5, "angle": -3.61 },
					{ "time": 1.6667, "angle": 3.69 }
				],
				"translate": [
					{ "time": 0, "x": 0, "y": 0, "curve": "stepped" },
					{ "time": 0.3333, "x": 0, "y": 0, "curve": "stepped" },
					{ "time": 0.6667, "x": 0, "y": 0, "curve": "stepped" },
					{ "time": 1, "x": 0, "y": 0, "curve": "stepped" },
					{ "time": 1.3333, "x": 0, "y": 0, "curve": "stepped" },
					{ "time": 1.6667, "x": 0, "y": 0 }
				],
				"scale": [
					{ "time": 0, "x": 1, "y": 1, "curve": "stepped" },
					{ "time": 0.3333, "x": 1, "y": 1, "curve": "stepped" },
					{ "time": 0.6667, "x": 1, "y": 1, "curve": "stepped" },
					{ "time": 1, "x": 1, "y": 1, "curve": "stepped" },
					{ "time": 1.3333, "x": 1, "y": 1, "curve": "stepped" },
					{ "time": 1.6667, "x": 1, "y": 1 }
				],
				"shear": [
					{ "time": 0, "x": 0, "y": 0, "curve": "stepped" },
					{ "time": 0.3333, "x": 0, "y": 0, "curve": "stepped" },
					{ "time": 0.6667, "x": 0, "y": 0, "curve": "stepped" },
					{ "time": 1, "x": 0, "y": 0, "curve": "stepped" },
					{ "time": 1.3333, "x": 0, "y": 0, "curve": "stepped" },
					{ "time": 1.6667, "x": 0, "y": 0 }
				]
			},
			"line body9": {
				"rotate": [
					{ "time": 0, "angle": 3.69 },
					{ "time": 0.1667, "angle": -3.61 },
					{ "time": 0.3333, "angle": 3.69 },
					{ "time": 0.5, "angle": -3.61 },
					{ "time": 0.6667, "angle": 3.69 },
					{ "time": 0.8333, "angle": -3.61 },
					{ "time": 1, "angle": 3.69 },
					{ "time": 1.1667, "angle": -3.61 },
					{ "time": 1.3333, "angle": 3.69 },
					{ "time": 1.5, "angle": -3.61 },
					{ "time": 1.6667, "angle": 3.69 }
				],
				"translate": [
					{ "time": 0, "x": 0, "y": 0, "curve": "stepped" },
					{ "time": 0.3333, "x": 0, "y": 0, "curve": "stepped" },
					{ "time": 0.6667, "x": 0, "y": 0, "curve": "stepped" },
					{ "time": 1, "x": 0, "y": 0, "curve": "stepped" },
					{ "time": 1.3333, "x": 0, "y": 0, "curve": "stepped" },
					{ "time": 1.6667, "x": 0, "y": 0 }
				],
				"scale": [
					{ "time": 0, "x": 1, "y": 1, "curve": "stepped" },
					{ "time": 0.3333, "x": 1, "y": 1, "curve": "stepped" },
					{ "time": 0.6667, "x": 1, "y": 1, "curve": "stepped" },
					{ "time": 1, "x": 1, "y": 1, "curve": "stepped" },
					{ "time": 1.3333, "x": 1, "y": 1, "curve": "stepped" },
					{ "time": 1.6667, "x": 1, "y": 1 }
				],
				"shear": [
					{ "time": 0, "x": 0, "y": 0, "curve": "stepped" },
					{ "time": 0.3333, "x": 0, "y": 0, "curve": "stepped" },
					{ "time": 0.6667, "x": 0, "y": 0, "curve": "stepped" },
					{ "time": 1, "x": 0, "y": 0, "curve": "stepped" },
					{ "time": 1.3333, "x": 0, "y": 0, "curve": "stepped" },
					{ "time": 1.6667, "x": 0, "y": 0 }
				]
			},
			"line leaf": {
				"rotate": [
					{ "time": 0, "angle": 0, "curve": "stepped" },
					{ "time": 0.6667, "angle": 0 }
				],
				"translate": [
					{ "time": 0, "x": 0, "y": 0, "curve": "stepped" },
					{ "time": 0.6667, "x": 0, "y": 0 }
				],
				"scale": [
					{ "time": 0, "x": 1, "y": 1, "curve": "stepped" },
					{ "time": 0.6667, "x": 1, "y": 1 }
				],
				"shear": [
					{ "time": 0, "x": 0, "y": 0, "curve": "stepped" },
					{ "time": 0.6667, "x": 0, "y": 0 }
				]
			},
			"line leaf2": {
				"rotate": [
					{ "time": 0, "angle": 0, "curve": "stepped" },
					{ "time": 0.6667, "angle": 0 }
				],
				"translate": [
					{ "time": 0, "x": 0, "y": 0, "curve": "stepped" },
					{ "time": 0.6667, "x": 0, "y": 0 }
				],
				"scale": [
					{ "time": 0, "x": 1, "y": 1, "curve": "stepped" },
					{ "time": 0.6667, "x": 1, "y": 1 }
				],
				"shear": [
					{ "time": 0, "x": 0, "y": 0, "curve": "stepped" },
					{ "time": 0.6667, "x": 0, "y": 0 }
				]
			},
			"Idle face": {
				"rotate": [
					{ "time": 0, "angle": 0, "curve": "stepped" },
					{ "time": 0.6667, "angle": 0 }
				],
				"translate": [
					{ "time": 0, "x": 0, "y": 0, "curve": "stepped" },
					{ "time": 0.6667, "x": 0, "y": 0 }
				],
				"scale": [
					{ "time": 0, "x": 1, "y": 1, "curve": "stepped" },
					{ "time": 0.6667, "x": 1, "y": 1 }
				],
				"shear": [
					{ "time": 0, "x": 0, "y": 0, "curve": "stepped" },
					{ "time": 0.6667, "x": 0, "y": 0 }
				]
			},
			"Smile mouth": {
				"rotate": [
					{ "time": 0, "angle": 0, "curve": "stepped" },
					{ "time": 0.6667, "angle": 0 }
				],
				"translate": [
					{ "time": 0, "x": 0, "y": 0, "curve": "stepped" },
					{ "time": 0.6667, "x": 0, "y": 0 }
				],
				"scale": [
					{ "time": 0, "x": 1, "y": 1, "curve": "stepped" },
					{ "time": 0.6667, "x": 1, "y": 1 }
				],
				"shear": [
					{ "time": 0, "x": 0, "y": 0, "curve": "stepped" },
					{ "time": 0.6667, "x": 0, "y": 0 }
				]
			},
			"Guance": {
				"rotate": [
					{ "time": 0, "angle": 0, "curve": "stepped" },
					{ "time": 0.6667, "angle": 0 }
				],
				"translate": [
					{ "time": 0, "x": 0, "y": 0, "curve": "stepped" },
					{ "time": 0.6667, "x": 0, "y": 0 }
				],
				"scale": [
					{ "time": 0, "x": 1, "y": 1, "curve": "stepped" },
					{ "time": 0.6667, "x": 1, "y": 1 }
				],
				"shear": [
					{ "time": 0, "x": 0, "y": 0, "curve": "stepped" },
					{ "time": 0.6667, "x": 0, "y": 0 }
				]
			}
		}
	},
	"idle": {
		"slots": {
			"Idle face": {
				"attachment": [
					{ "time": 0.1333, "name": "Sleeping face" },
					{ "time": 0.2333, "name": "Sleeping face" },
					{ "time": 1, "name": "Idle face" },
					{ "time": 2, "name": "Idle face" }
				]
			},
			"ciglia": {
				"attachment": [
					{ "time": 0.1333, "name": null },
					{ "time": 1, "name": "ciglia" }
				]
			}
		},
		"bones": {
			"line body2": {
				"rotate": [
					{ "time": 0, "angle": 11.8 },
					{ "time": 1, "angle": -12.3 },
					{ "time": 2, "angle": 11.8 }
				],
				"translate": [
					{ "time": 0, "x": 0, "y": 0 },
					{ "time": 0.2333, "x": 64.71, "y": 32.69 },
					{ "time": 1.3333, "x": 32, "y": 30.55 },
					{ "time": 2, "x": 0, "y": 0 }
				],
				"scale": [
					{ "time": 0, "x": 1, "y": 1, "curve": "stepped" },
					{ "time": 2, "x": 1, "y": 1 }
				],
				"shear": [
					{ "time": 0, "x": 0, "y": 0, "curve": "stepped" },
					{ "time": 2, "x": 0, "y": 0 }
				]
			},
			"line body4": {
				"rotate": [
					{
						"time": 0,
						"angle": 11.8,
						"curve": [ 0.157, 0.07, 0.481, 0.82 ]
					},
					{ "time": 1, "angle": -12.3 },
					{ "time": 2, "angle": 11.8 }
				],
				"translate": [
					{ "time": 0, "x": 0, "y": 0, "curve": "stepped" },
					{ "time": 2, "x": 0, "y": 0 }
				],
				"scale": [
					{ "time": 0, "x": 1, "y": 1, "curve": "stepped" },
					{ "time": 2, "x": 1, "y": 1 }
				],
				"shear": [
					{ "time": 0, "x": 0, "y": 0, "curve": "stepped" },
					{ "time": 2, "x": 0, "y": 0 }
				]
			},
			"line body5": {
				"rotate": [
					{
						"time": 0,
						"angle": 11.8,
						"curve": [ 0.157, 0.07, 0.481, 0.82 ]
					},
					{ "time": 1, "angle": -12.3 },
					{ "time": 2, "angle": 11.8 }
				],
				"translate": [
					{ "time": 0, "x": 0, "y": 0, "curve": "stepped" },
					{ "time": 2, "x": 0, "y": 0 }
				],
				"scale": [
					{ "time": 0, "x": 1, "y": 1, "curve": "stepped" },
					{ "time": 2, "x": 1, "y": 1 }
				],
				"shear": [
					{ "time": 0, "x": 0, "y": 0, "curve": "stepped" },
					{ "time": 2, "x": 0, "y": 0 }
				]
			},
			"line body6": {
				"rotate": [
					{
						"time": 0,
						"angle": 11.8,
						"curve": [ 0.157, 0.07, 0.481, 0.82 ]
					},
					{ "time": 1, "angle": -12.3 },
					{ "time": 2, "angle": 11.8 }
				],
				"translate": [
					{ "time": 0, "x": 0, "y": 0, "curve": "stepped" },
					{ "time": 2, "x": 0, "y": 0 }
				],
				"scale": [
					{ "time": 0, "x": 1, "y": 1, "curve": "stepped" },
					{ "time": 2, "x": 1, "y": 1 }
				],
				"shear": [
					{ "time": 0, "x": 0, "y": 0, "curve": "stepped" },
					{ "time": 2, "x": 0, "y": 0 }
				]
			},
			"line body7": {
				"rotate": [
					{
						"time": 0,
						"angle": 11.8,
						"curve": [ 0.157, 0.07, 0.481, 0.82 ]
					},
					{ "time": 1, "angle": -12.3 },
					{ "time": 2, "angle": 11.8 }
				],
				"translate": [
					{ "time": 0, "x": 0, "y": 0, "curve": "stepped" },
					{ "time": 2, "x": 0, "y": 0 }
				],
				"scale": [
					{ "time": 0, "x": 1, "y": 1, "curve": "stepped" },
					{ "time": 2, "x": 1, "y": 1 }
				],
				"shear": [
					{ "time": 0, "x": 0, "y": 0, "curve": "stepped" },
					{ "time": 2, "x": 0, "y": 0 }
				]
			},
			"line body8": {
				"rotate": [
					{
						"time": 0,
						"angle": 11.8,
						"curve": [ 0.157, 0.07, 0.481, 0.82 ]
					},
					{ "time": 1, "angle": -12.3 },
					{ "time": 2, "angle": 11.8 }
				],
				"translate": [
					{ "time": 0, "x": 0, "y": 0, "curve": "stepped" },
					{ "time": 2, "x": 0, "y": 0 }
				],
				"scale": [
					{ "time": 0, "x": 1, "y": 1, "curve": "stepped" },
					{ "time": 2, "x": 1, "y": 1 }
				],
				"shear": [
					{ "time": 0, "x": 0, "y": 0, "curve": "stepped" },
					{ "time": 2, "x": 0, "y": 0 }
				]
			},
			"line body9": {
				"rotate": [
					{
						"time": 0,
						"angle": 11.8,
						"curve": [ 0.157, 0.07, 0.481, 0.82 ]
					},
					{ "time": 1, "angle": -12.3 },
					{ "time": 2, "angle": 11.8 }
				],
				"translate": [
					{ "time": 0, "x": 0, "y": 0, "curve": "stepped" },
					{ "time": 2, "x": 0, "y": 0 }
				],
				"scale": [
					{ "time": 0, "x": 1, "y": 1, "curve": "stepped" },
					{ "time": 2, "x": 1, "y": 1 }
				],
				"shear": [
					{ "time": 0, "x": 0, "y": 0, "curve": "stepped" },
					{ "time": 2, "x": 0, "y": 0 }
				]
			},
			"line body": {
				"rotate": [
					{ "time": 0, "angle": 0, "curve": "stepped" },
					{ "time": 2, "angle": 0 }
				],
				"translate": [
					{ "time": 0, "x": 0, "y": 0, "curve": "stepped" },
					{ "time": 2, "x": 0, "y": 0 }
				],
				"scale": [
					{
						"time": 0,
						"x": 1,
						"y": 1,
						"curve": [ 0.287, 0.14, 0.62, 0.49 ]
					},
					{
						"time": 1,
						"x": 1,
						"y": 0.917,
						"curve": [ 0.192, 0.23, 0.52, 0.84 ]
					},
					{ "time": 2, "x": 1, "y": 1 }
				],
				"shear": [
					{ "time": 0, "x": 0, "y": 0, "curve": "stepped" },
					{ "time": 2, "x": 0, "y": 0 }
				]
			},
			"line leaf": {
				"rotate": [
					{ "time": 0, "angle": 0, "curve": "stepped" },
					{ "time": 2, "angle": 0 }
				],
				"translate": [
					{ "time": 0, "x": 0, "y": 0, "curve": "stepped" },
					{ "time": 2, "x": 0, "y": 0 }
				],
				"scale": [
					{ "time": 0, "x": 1, "y": 1, "curve": "stepped" },
					{ "time": 2, "x": 1, "y": 1 }
				],
				"shear": [
					{ "time": 0, "x": 0, "y": 0, "curve": "stepped" },
					{ "time": 2, "x": 0, "y": 0 }
				]
			},
			"line leaf2": {
				"rotate": [
					{ "time": 0, "angle": 0, "curve": "stepped" },
					{ "time": 2, "angle": 0 }
				],
				"translate": [
					{ "time": 0, "x": 0, "y": 0, "curve": "stepped" },
					{ "time": 2, "x": 0, "y": 0 }
				],
				"scale": [
					{ "time": 0, "x": 1, "y": 1, "curve": "stepped" },
					{ "time": 2, "x": 1, "y": 1 }
				],
				"shear": [
					{ "time": 0, "x": 0, "y": 0, "curve": "stepped" },
					{ "time": 2, "x": 0, "y": 0 }
				]
			},
			"Smile mouth": {
				"rotate": [
					{ "time": 0, "angle": 0, "curve": "stepped" },
					{ "time": 2, "angle": 0 }
				],
				"translate": [
					{ "time": 0, "x": 0, "y": 0, "curve": "stepped" },
					{ "time": 2, "x": 0, "y": 0 }
				],
				"scale": [
					{ "time": 0, "x": 1, "y": 1, "curve": "stepped" },
					{ "time": 2, "x": 1, "y": 1 }
				],
				"shear": [
					{ "time": 0, "x": 0, "y": 0, "curve": "stepped" },
					{ "time": 2, "x": 0, "y": 0 }
				]
			},
			"Idle face": {
				"rotate": [
					{ "time": 0, "angle": 0, "curve": "stepped" },
					{ "time": 2, "angle": 0 }
				],
				"translate": [
					{ "time": 0, "x": 0, "y": 0, "curve": "stepped" },
					{ "time": 2, "x": 0, "y": 0 }
				],
				"scale": [
					{ "time": 0, "x": 1, "y": 1, "curve": "stepped" },
					{ "time": 2, "x": 1, "y": 1 }
				],
				"shear": [
					{ "time": 0, "x": 0, "y": 0, "curve": "stepped" },
					{ "time": 2, "x": 0, "y": 0 }
				]
			},
			"Guance": {
				"rotate": [
					{ "time": 0, "angle": 0, "curve": "stepped" },
					{ "time": 2, "angle": 0 }
				],
				"translate": [
					{ "time": 0, "x": 0, "y": 0, "curve": "stepped" },
					{ "time": 2, "x": 0, "y": 0 }
				],
				"scale": [
					{ "time": 0, "x": 1, "y": 1, "curve": "stepped" },
					{ "time": 2, "x": 1, "y": 1 }
				],
				"shear": [
					{ "time": 0, "x": 0, "y": 0, "curve": "stepped" },
					{ "time": 2, "x": 0, "y": 0 }
				]
			},
			"root": {
				"rotate": [
					{ "time": 0, "angle": 0, "curve": "stepped" },
					{ "time": 2, "angle": 0 }
				],
				"translate": [
					{ "time": 0, "x": 0, "y": 0, "curve": "stepped" },
					{ "time": 2, "x": 0, "y": 0 }
				],
				"scale": [
					{ "time": 0, "x": 1, "y": 1, "curve": "stepped" },
					{ "time": 2, "x": 1, "y": 1 }
				],
				"shear": [
					{ "time": 0, "x": 0, "y": 0, "curve": "stepped" },
					{ "time": 2, "x": 0, "y": 0 }
				]
			}
		}
	},
	"intermezzo dormita": {
		"slots": {
			"Idle face": {
				"attachment": [
					{ "time": 1, "name": "Idle face" },
					{ "time": 1.5, "name": "Sleeping face" },
					{ "time": 2.5, "name": "Sleeping face" }
				]
			},
			"Smile mouth": {
				"attachment": [
					{ "time": 2.5, "name": "Smile mouth" }
				]
			},
			"ciglia": {
				"attachment": [
					{ "time": 1, "name": "ciglia" },
					{ "time": 1.5, "name": null }
				]
			}
		},
		"bones": {
			"line body6": {
				"rotate": [
					{
						"time": 0,
						"angle": 11.8,
						"curve": [ 0.157, 0.07, 0.481, 0.82 ]
					},
					{ "time": 1, "angle": -12.3 },
					{ "time": 2.5, "angle": 27.52 }
				],
				"translate": [
					{ "time": 0, "x": 0, "y": 0, "curve": "stepped" },
					{ "time": 2.5, "x": 0, "y": 0 }
				],
				"scale": [
					{ "time": 0, "x": 1, "y": 1, "curve": "stepped" },
					{ "time": 2.5, "x": 1, "y": 1 }
				],
				"shear": [
					{ "time": 0, "x": 0, "y": 0, "curve": "stepped" },
					{ "time": 2.5, "x": 0, "y": 0 }
				]
			},
			"line body5": {
				"rotate": [
					{
						"time": 0,
						"angle": 11.8,
						"curve": [ 0.157, 0.07, 0.481, 0.82 ]
					},
					{ "time": 1, "angle": -12.3 },
					{ "time": 2.5, "angle": 3.28 }
				],
				"translate": [
					{ "time": 0, "x": 0, "y": 0, "curve": "stepped" },
					{ "time": 2.5, "x": 0, "y": 0 }
				],
				"scale": [
					{ "time": 0, "x": 1, "y": 1, "curve": "stepped" },
					{ "time": 2.5, "x": 1, "y": 1 }
				],
				"shear": [
					{ "time": 0, "x": 0, "y": 0, "curve": "stepped" },
					{ "time": 2.5, "x": 0, "y": 0 }
				]
			},
			"line body4": {
				"rotate": [
					{
						"time": 0,
						"angle": 11.8,
						"curve": [ 0.157, 0.07, 0.481, 0.82 ]
					},
					{ "time": 1, "angle": -12.3 },
					{ "time": 2.5, "angle": 27.52 }
				],
				"translate": [
					{ "time": 0, "x": 0, "y": 0, "curve": "stepped" },
					{ "time": 2.5, "x": 0, "y": 0 }
				],
				"scale": [
					{ "time": 0, "x": 1, "y": 1, "curve": "stepped" },
					{ "time": 2.5, "x": 1, "y": 1 }
				],
				"shear": [
					{ "time": 0, "x": 0, "y": 0, "curve": "stepped" },
					{ "time": 2.5, "x": 0, "y": 0 }
				]
			},
			"Guance": {
				"rotate": [
					{ "time": 0, "angle": 0 }
				],
				"translate": [
					{ "time": 0, "x": 0, "y": 0 }
				],
				"scale": [
					{ "time": 0, "x": 1, "y": 1 }
				],
				"shear": [
					{ "time": 0, "x": 0, "y": 0 }
				]
			},
			"line body9": {
				"rotate": [
					{
						"time": 0,
						"angle": 11.8,
						"curve": [ 0.157, 0.07, 0.481, 0.82 ]
					},
					{ "time": 1, "angle": -12.3 },
					{ "time": 2.5, "angle": 27.52 }
				],
				"translate": [
					{ "time": 0, "x": 0, "y": 0, "curve": "stepped" },
					{ "time": 2.5, "x": 0, "y": 0 }
				],
				"scale": [
					{ "time": 0, "x": 1, "y": 1, "curve": "stepped" },
					{ "time": 2.5, "x": 1, "y": 1 }
				],
				"shear": [
					{ "time": 0, "x": 0, "y": 0, "curve": "stepped" },
					{ "time": 2.5, "x": 0, "y": 0 }
				]
			},
			"line body": {
				"rotate": [
					{ "time": 0, "angle": 0 }
				],
				"translate": [
					{ "time": 0, "x": 0, "y": 0 }
				],
				"scale": [
					{
						"time": 0,
						"x": 1,
						"y": 1,
						"curve": [ 0.287, 0.14, 0.62, 0.49 ]
					},
					{ "time": 1, "x": 1, "y": 0.917 }
				],
				"shear": [
					{ "time": 0, "x": 0, "y": 0 }
				]
			},
			"root": {
				"rotate": [
					{ "time": 0, "angle": 0 }
				],
				"translate": [
					{ "time": 0, "x": 0, "y": 0 }
				],
				"scale": [
					{ "time": 0, "x": 1, "y": 1 }
				],
				"shear": [
					{ "time": 0, "x": 0, "y": 0 }
				]
			},
			"line leaf": {
				"rotate": [
					{ "time": 0, "angle": 0 }
				],
				"translate": [
					{ "time": 0, "x": 0, "y": 0 }
				],
				"scale": [
					{ "time": 0, "x": 1, "y": 1 }
				],
				"shear": [
					{ "time": 0, "x": 0, "y": 0 }
				]
			},
			"line body7": {
				"rotate": [
					{
						"time": 0,
						"angle": 11.8,
						"curve": [ 0.157, 0.07, 0.481, 0.82 ]
					},
					{ "time": 1, "angle": -12.3 },
					{ "time": 2.5, "angle": 27.52 }
				],
				"translate": [
					{ "time": 0, "x": 0, "y": 0, "curve": "stepped" },
					{ "time": 2.5, "x": 0, "y": 0 }
				],
				"scale": [
					{ "time": 0, "x": 1, "y": 1, "curve": "stepped" },
					{ "time": 2.5, "x": 1, "y": 1 }
				],
				"shear": [
					{ "time": 0, "x": 0, "y": 0, "curve": "stepped" },
					{ "time": 2.5, "x": 0, "y": 0 }
				]
			},
			"line body2": {
				"rotate": [
					{ "time": 0, "angle": 11.8 },
					{ "time": 1, "angle": -12.3 },
					{ "time": 2.5, "angle": 3.28 }
				],
				"translate": [
					{ "time": 0, "x": 0, "y": 0, "curve": "stepped" },
					{ "time": 2.5, "x": 0, "y": 0 }
				],
				"scale": [
					{ "time": 0, "x": 1, "y": 1, "curve": "stepped" },
					{ "time": 2.5, "x": 1, "y": 1 }
				],
				"shear": [
					{ "time": 0, "x": 0, "y": 0, "curve": "stepped" },
					{ "time": 2.5, "x": 0, "y": 0 }
				]
			},
			"Smile mouth": {
				"rotate": [
					{ "time": 0, "angle": 0 }
				],
				"translate": [
					{ "time": 0, "x": 0, "y": 0 }
				],
				"scale": [
					{ "time": 0, "x": 1, "y": 1 }
				],
				"shear": [
					{ "time": 0, "x": 0, "y": 0 }
				]
			},
			"Idle face": {
				"rotate": [
					{ "time": 0, "angle": 0 }
				],
				"translate": [
					{ "time": 0, "x": 0, "y": 0 }
				],
				"scale": [
					{ "time": 0, "x": 1, "y": 1 }
				],
				"shear": [
					{ "time": 0, "x": 0, "y": 0 }
				]
			},
			"line leaf2": {
				"rotate": [
					{ "time": 0, "angle": 0 }
				],
				"translate": [
					{ "time": 0, "x": 0, "y": 0 }
				],
				"scale": [
					{ "time": 0, "x": 1, "y": 1 }
				],
				"shear": [
					{ "time": 0, "x": 0, "y": 0 }
				]
			},
			"line body8": {
				"rotate": [
					{
						"time": 0,
						"angle": 11.8,
						"curve": [ 0.157, 0.07, 0.481, 0.82 ]
					},
					{ "time": 1, "angle": -12.3 },
					{ "time": 2.5, "angle": 27.52 }
				],
				"translate": [
					{ "time": 0, "x": 0, "y": 0, "curve": "stepped" },
					{ "time": 2.5, "x": 0, "y": 0 }
				],
				"scale": [
					{ "time": 0, "x": 1, "y": 1, "curve": "stepped" },
					{ "time": 2.5, "x": 1, "y": 1 }
				],
				"shear": [
					{ "time": 0, "x": 0, "y": 0, "curve": "stepped" },
					{ "time": 2.5, "x": 0, "y": 0 }
				]
			}
		}
	},
	"intermezzo triste": {
		"slots": {
			"Idle face": {
				"attachment": [
					{ "time": 0.1333, "name": "Sleeping face" },
					{ "time": 1, "name": "Idle face" },
					{ "time": 2, "name": "Sadness face 2" }
				]
			},
			"Smile mouth": {
				"attachment": [
					{ "time": 2, "name": "sadness mouth" }
				]
			},
			"ciglia": {
				"attachment": [
					{ "time": 0.1333, "name": null }
				]
			}
		},
		"bones": {
			"line body2": {
				"rotate": [
					{ "time": 0, "angle": 11.8 },
					{ "time": 1, "angle": -12.3 },
					{ "time": 2, "angle": 3.28 }
				],
				"translate": [
					{ "time": 0, "x": 0, "y": 0, "curve": "stepped" },
					{ "time": 2, "x": 0, "y": 0 }
				],
				"scale": [
					{ "time": 0, "x": 1, "y": 1, "curve": "stepped" },
					{ "time": 2, "x": 1, "y": 1 }
				],
				"shear": [
					{ "time": 0, "x": 0, "y": 0, "curve": "stepped" },
					{ "time": 2, "x": 0, "y": 0 }
				]
			},
			"line leaf2": {
				"rotate": [
					{ "time": 0, "angle": 0 }
				],
				"translate": [
					{ "time": 0, "x": 0, "y": 0 }
				],
				"scale": [
					{ "time": 0, "x": 1, "y": 1 }
				],
				"shear": [
					{ "time": 0, "x": 0, "y": 0 }
				]
			},
			"Smile mouth": {
				"rotate": [
					{ "time": 0, "angle": 0 }
				],
				"translate": [
					{ "time": 0, "x": 0, "y": 0 }
				],
				"scale": [
					{ "time": 0, "x": 1, "y": 1 }
				],
				"shear": [
					{ "time": 0, "x": 0, "y": 0 }
				]
			},
			"Idle face": {
				"rotate": [
					{ "time": 0, "angle": 0 }
				],
				"translate": [
					{ "time": 0, "x": 0, "y": 0 }
				],
				"scale": [
					{ "time": 0, "x": 1, "y": 1 }
				],
				"shear": [
					{ "time": 0, "x": 0, "y": 0 }
				]
			},
			"line body4": {
				"rotate": [
					{
						"time": 0,
						"angle": 11.8,
						"curve": [ 0.157, 0.07, 0.481, 0.82 ]
					},
					{ "time": 1, "angle": -12.3 },
					{ "time": 2, "angle": 27.52 }
				],
				"translate": [
					{ "time": 0, "x": 0, "y": 0, "curve": "stepped" },
					{ "time": 2, "x": 0, "y": 0 }
				],
				"scale": [
					{ "time": 0, "x": 1, "y": 1, "curve": "stepped" },
					{ "time": 2, "x": 1, "y": 1 }
				],
				"shear": [
					{ "time": 0, "x": 0, "y": 0, "curve": "stepped" },
					{ "time": 2, "x": 0, "y": 0 }
				]
			},
			"root": {
				"rotate": [
					{ "time": 0, "angle": 0 }
				],
				"translate": [
					{ "time": 0, "x": 0, "y": 0 }
				],
				"scale": [
					{ "time": 0, "x": 1, "y": 1 }
				],
				"shear": [
					{ "time": 0, "x": 0, "y": 0 }
				]
			},
			"line body6": {
				"rotate": [
					{
						"time": 0,
						"angle": 11.8,
						"curve": [ 0.157, 0.07, 0.481, 0.82 ]
					},
					{ "time": 1, "angle": -12.3 },
					{ "time": 2, "angle": 27.52 }
				],
				"translate": [
					{ "time": 0, "x": 0, "y": 0, "curve": "stepped" },
					{ "time": 2, "x": 0, "y": 0 }
				],
				"scale": [
					{ "time": 0, "x": 1, "y": 1, "curve": "stepped" },
					{ "time": 2, "x": 1, "y": 1 }
				],
				"shear": [
					{ "time": 0, "x": 0, "y": 0, "curve": "stepped" },
					{ "time": 2, "x": 0, "y": 0 }
				]
			},
			"line body": {
				"rotate": [
					{ "time": 0, "angle": 0 }
				],
				"translate": [
					{ "time": 0, "x": 0, "y": 0 }
				],
				"scale": [
					{
						"time": 0,
						"x": 1,
						"y": 1,
						"curve": [ 0.287, 0.14, 0.62, 0.49 ]
					},
					{ "time": 1, "x": 1, "y": 0.917 }
				],
				"shear": [
					{ "time": 0, "x": 0, "y": 0 }
				]
			},
			"Guance": {
				"rotate": [
					{ "time": 0, "angle": 0 }
				],
				"translate": [
					{ "time": 0, "x": 0, "y": 0 }
				],
				"scale": [
					{ "time": 0, "x": 1, "y": 1 }
				],
				"shear": [
					{ "time": 0, "x": 0, "y": 0 }
				]
			},
			"line body5": {
				"rotate": [
					{
						"time": 0,
						"angle": 11.8,
						"curve": [ 0.157, 0.07, 0.481, 0.82 ]
					},
					{ "time": 1, "angle": -12.3 },
					{ "time": 2, "angle": 3.28 }
				],
				"translate": [
					{ "time": 0, "x": 0, "y": 0, "curve": "stepped" },
					{ "time": 2, "x": 0, "y": 0 }
				],
				"scale": [
					{ "time": 0, "x": 1, "y": 1, "curve": "stepped" },
					{ "time": 2, "x": 1, "y": 1 }
				],
				"shear": [
					{ "time": 0, "x": 0, "y": 0, "curve": "stepped" },
					{ "time": 2, "x": 0, "y": 0 }
				]
			},
			"line body7": {
				"rotate": [
					{
						"time": 0,
						"angle": 11.8,
						"curve": [ 0.157, 0.07, 0.481, 0.82 ]
					},
					{ "time": 1, "angle": -12.3 },
					{ "time": 2, "angle": 27.52 }
				],
				"translate": [
					{ "time": 0, "x": 0, "y": 0, "curve": "stepped" },
					{ "time": 2, "x": 0, "y": 0 }
				],
				"scale": [
					{ "time": 0, "x": 1, "y": 1, "curve": "stepped" },
					{ "time": 2, "x": 1, "y": 1 }
				],
				"shear": [
					{ "time": 0, "x": 0, "y": 0, "curve": "stepped" },
					{ "time": 2, "x": 0, "y": 0 }
				]
			},
			"line body9": {
				"rotate": [
					{
						"time": 0,
						"angle": 11.8,
						"curve": [ 0.157, 0.07, 0.481, 0.82 ]
					},
					{ "time": 1, "angle": -12.3 },
					{ "time": 2, "angle": 27.52 }
				],
				"translate": [
					{ "time": 0, "x": 0, "y": 0, "curve": "stepped" },
					{ "time": 2, "x": 0, "y": 0 }
				],
				"scale": [
					{ "time": 0, "x": 1, "y": 1, "curve": "stepped" },
					{ "time": 2, "x": 1, "y": 1 }
				],
				"shear": [
					{ "time": 0, "x": 0, "y": 0, "curve": "stepped" },
					{ "time": 2, "x": 0, "y": 0 }
				]
			},
			"line body8": {
				"rotate": [
					{
						"time": 0,
						"angle": 11.8,
						"curve": [ 0.157, 0.07, 0.481, 0.82 ]
					},
					{ "time": 1, "angle": -12.3 },
					{ "time": 2, "angle": 27.52 }
				],
				"translate": [
					{ "time": 0, "x": 0, "y": 0, "curve": "stepped" },
					{ "time": 2, "x": 0, "y": 0 }
				],
				"scale": [
					{ "time": 0, "x": 1, "y": 1, "curve": "stepped" },
					{ "time": 2, "x": 1, "y": 1 }
				],
				"shear": [
					{ "time": 0, "x": 0, "y": 0, "curve": "stepped" },
					{ "time": 2, "x": 0, "y": 0 }
				]
			},
			"line leaf": {
				"rotate": [
					{ "time": 0, "angle": 0 }
				],
				"translate": [
					{ "time": 0, "x": 0, "y": 0 }
				],
				"scale": [
					{ "time": 0, "x": 1, "y": 1 }
				],
				"shear": [
					{ "time": 0, "x": 0, "y": 0 }
				]
			}
		}
	},
	"triste": {
		"slots": {
			"Idle face": {
				"attachment": [
					{ "time": 0, "name": "Sadness face 2" }
				]
			},
			"Smile mouth": {
				"attachment": [
					{ "time": 0, "name": "sadness mouth" }
				]
			}
		},
		"bones": {
			"root": {
				"rotate": [
					{ "time": 0, "angle": 0 }
				],
				"translate": [
					{ "time": 0, "x": 0, "y": 0 }
				],
				"scale": [
					{ "time": 0, "x": 1, "y": 1 }
				],
				"shear": [
					{ "time": 0, "x": 0, "y": 0 }
				]
			},
			"line body": {
				"rotate": [
					{ "time": 0, "angle": 0, "curve": "stepped" },
					{ "time": 1.3333, "angle": 0 }
				],
				"translate": [
					{ "time": 0, "x": 0, "y": 0, "curve": "stepped" },
					{ "time": 1.3333, "x": 0, "y": 0 }
				],
				"scale": [
					{ "time": 0, "x": 1, "y": 1 },
					{ "time": 0.6667, "x": 1, "y": 0.918 },
					{ "time": 1.3333, "x": 1, "y": 1 }
				],
				"shear": [
					{ "time": 0, "x": 0, "y": 0, "curve": "stepped" },
					{ "time": 1.3333, "x": 0, "y": 0 }
				]
			},
			"line body2": {
				"rotate": [
					{ "time": 0, "angle": 3.28 },
					{ "time": 0.8, "angle": -3.09 },
					{ "time": 2, "angle": 3.28 }
				],
				"translate": [
					{ "time": 0, "x": 0, "y": 0, "curve": "stepped" },
					{ "time": 2, "x": 0, "y": 0 }
				],
				"scale": [
					{ "time": 0, "x": 1, "y": 1, "curve": "stepped" },
					{ "time": 2, "x": 1, "y": 1 }
				],
				"shear": [
					{ "time": 0, "x": 0, "y": 0, "curve": "stepped" },
					{ "time": 2, "x": 0, "y": 0 }
				]
			},
			"line body4": {
				"rotate": [
					{ "time": 0, "angle": 27.52 },
					{ "time": 0.8, "angle": 29.36 },
					{ "time": 2, "angle": 27.52 }
				],
				"translate": [
					{ "time": 0, "x": 0, "y": 0, "curve": "stepped" },
					{ "time": 2, "x": 0, "y": 0 }
				],
				"scale": [
					{ "time": 0, "x": 1, "y": 1, "curve": "stepped" },
					{ "time": 2, "x": 1, "y": 1 }
				],
				"shear": [
					{ "time": 0, "x": 0, "y": 0, "curve": "stepped" },
					{ "time": 2, "x": 0, "y": 0 }
				]
			},
			"line body5": {
				"rotate": [
					{ "time": 0, "angle": 3.28 },
					{ "time": 0.8, "angle": -3.09 },
					{ "time": 2, "angle": 3.28 }
				],
				"translate": [
					{ "time": 0, "x": 0, "y": 0, "curve": "stepped" },
					{ "time": 2, "x": 0, "y": 0 }
				],
				"scale": [
					{ "time": 0, "x": 1, "y": 1, "curve": "stepped" },
					{ "time": 2, "x": 1, "y": 1 }
				],
				"shear": [
					{ "time": 0, "x": 0, "y": 0, "curve": "stepped" },
					{ "time": 2, "x": 0, "y": 0 }
				]
			},
			"line body6": {
				"rotate": [
					{ "time": 0, "angle": 27.52 },
					{ "time": 0.8, "angle": 29.36 },
					{ "time": 2, "angle": 27.52 }
				],
				"translate": [
					{ "time": 0, "x": 0, "y": 0, "curve": "stepped" },
					{ "time": 2, "x": 0, "y": 0 }
				],
				"scale": [
					{ "time": 0, "x": 1, "y": 1, "curve": "stepped" },
					{ "time": 2, "x": 1, "y": 1 }
				],
				"shear": [
					{ "time": 0, "x": 0, "y": 0, "curve": "stepped" },
					{ "time": 2, "x": 0, "y": 0 }
				]
			},
			"line body7": {
				"rotate": [
					{ "time": 0, "angle": 27.52 },
					{ "time": 0.8, "angle": 29.36 },
					{ "time": 2, "angle": 27.52 }
				],
				"translate": [
					{ "time": 0, "x": 0, "y": 0, "curve": "stepped" },
					{ "time": 2, "x": 0, "y": 0 }
				],
				"scale": [
					{ "time": 0, "x": 1, "y": 1, "curve": "stepped" },
					{ "time": 2, "x": 1, "y": 1 }
				],
				"shear": [
					{ "time": 0, "x": 0, "y": 0, "curve": "stepped" },
					{ "time": 2, "x": 0, "y": 0 }
				]
			},
			"line body8": {
				"rotate": [
					{ "time": 0, "angle": 27.52 },
					{ "time": 0.8, "angle": 29.36 },
					{ "time": 2, "angle": 27.52 }
				],
				"translate": [
					{ "time": 0, "x": 0, "y": 0, "curve": "stepped" },
					{ "time": 2, "x": 0, "y": 0 }
				],
				"scale": [
					{ "time": 0, "x": 1, "y": 1, "curve": "stepped" },
					{ "time": 2, "x": 1, "y": 1 }
				],
				"shear": [
					{ "time": 0, "x": 0, "y": 0, "curve": "stepped" },
					{ "time": 2, "x": 0, "y": 0 }
				]
			},
			"line body9": {
				"rotate": [
					{ "time": 0, "angle": 27.52 },
					{ "time": 0.8, "angle": 29.36 },
					{ "time": 2, "angle": 27.52 }
				],
				"translate": [
					{ "time": 0, "x": 0, "y": 0, "curve": "stepped" },
					{ "time": 2, "x": 0, "y": 0 }
				],
				"scale": [
					{ "time": 0, "x": 1, "y": 1, "curve": "stepped" },
					{ "time": 2, "x": 1, "y": 1 }
				],
				"shear": [
					{ "time": 0, "x": 0, "y": 0, "curve": "stepped" },
					{ "time": 2, "x": 0, "y": 0 }
				]
			},
			"line leaf": {
				"rotate": [
					{ "time": 0, "angle": 0 }
				],
				"translate": [
					{ "time": 0, "x": 0, "y": 0 }
				],
				"scale": [
					{ "time": 0, "x": 1, "y": 1 }
				],
				"shear": [
					{ "time": 0, "x": 0, "y": 0 }
				]
			},
			"line leaf2": {
				"rotate": [
					{ "time": 0, "angle": 0 }
				],
				"translate": [
					{ "time": 0, "x": 0, "y": 0 }
				],
				"scale": [
					{ "time": 0, "x": 1, "y": 1 }
				],
				"shear": [
					{ "time": 0, "x": 0, "y": 0 }
				]
			},
			"Idle face": {
				"rotate": [
					{ "time": 0, "angle": 0 }
				],
				"translate": [
					{ "time": 0, "x": 0, "y": 0 }
				],
				"scale": [
					{ "time": 0, "x": 1, "y": 1 }
				],
				"shear": [
					{ "time": 0, "x": 0, "y": 0 }
				]
			},
			"Smile mouth": {
				"rotate": [
					{ "time": 0, "angle": 0 }
				],
				"translate": [
					{ "time": 0, "x": 0, "y": 0 }
				],
				"scale": [
					{ "time": 0, "x": 1, "y": 1 }
				],
				"shear": [
					{ "time": 0, "x": 0, "y": 0 }
				]
			},
			"Guance": {
				"rotate": [
					{ "time": 0, "angle": 0 }
				],
				"translate": [
					{ "time": 0, "x": 0, "y": 0 }
				],
				"scale": [
					{ "time": 0, "x": 1, "y": 1 }
				],
				"shear": [
					{ "time": 0, "x": 0, "y": 0 }
				]
			},
			"ciglia f": {
				"rotate": [
					{ "time": 0, "angle": 0, "curve": "stepped" },
					{ "time": 2, "angle": 0 }
				],
				"translate": [
					{ "time": 0, "x": -20.49, "y": -1.79, "curve": "stepped" },
					{ "time": 2, "x": -20.49, "y": -1.79 }
				]
			}
		}
	}
}
}